xontrib/autojump.py
xontrib_autojump-1.4.dist-info/LICENSE
xontrib_autojump-1.4.dist-info/METADATA
xontrib_autojump-1.4.dist-info/WHEEL
xontrib_autojump-1.4.dist-info/top_level.txt
xontrib_autojump-1.4.dist-info/RECORD
