Metadata-Version: 2.1
Name: xontrib-autojump
Version: 1.4
Summary: autojump support for xonsh
Home-page: https://github.com/willsALMANJ/autojump-xonsh
Author: Will Shanks
Author-email: wshaos@posteo.net
License: GPLv3+
Platform: any
License-File: LICENSE
